paytm_api/__init__.py
paytm_api/core.py
paytm_api-1.2.7.dist-info/METADATA
paytm_api-1.2.7.dist-info/WHEEL
paytm_api-1.2.7.dist-info/top_level.txt
paytm_api-1.2.7.dist-info/RECORD
