Metadata-Version: 2.4
Name: paytm-api
Version: 1.2.7
Summary: Simple Python library to verify Paytm Merchant transaction status
Home-page: https://github.com/DragoServer/paytm_api
Author: DragoServer
Author-email: drago.ftw@litedns.xyz
License: MIT
Classifier: Programming Language :: Python :: 3
Classifier: License :: OSI Approved :: MIT License
Classifier: Operating System :: OS Independent
Requires-Python: >=3.7
Requires-Dist: requests
